swarms_client/__init__.py
swarms_client/_base_client.py
swarms_client/_client.py
swarms_client/_compat.py
swarms_client/_constants.py
swarms_client/_exceptions.py
swarms_client/_files.py
swarms_client/_models.py
swarms_client/_qs.py
swarms_client/_resource.py
swarms_client/_response.py
swarms_client/_streaming.py
swarms_client/_types.py
swarms_client/_version.py
swarms_client/py.typed
swarms_client/_utils/__init__.py
swarms_client/_utils/_logs.py
swarms_client/_utils/_proxy.py
swarms_client/_utils/_reflection.py
swarms_client/_utils/_resources_proxy.py
swarms_client/_utils/_streams.py
swarms_client/_utils/_sync.py
swarms_client/_utils/_transform.py
swarms_client/_utils/_typing.py
swarms_client/_utils/_utils.py
swarms_client/lib/.keep
swarms_client/resources/__init__.py
swarms_client/resources/health.py
swarms_client/resources/models.py
swarms_client/resources/agent/__init__.py
swarms_client/resources/agent/agent.py
swarms_client/resources/agent/batch.py
swarms_client/resources/swarms/__init__.py
swarms_client/resources/swarms/batch.py
swarms_client/resources/swarms/swarms.py
swarms_client/types/__init__.py
swarms_client/types/agent_completion_param.py
swarms_client/types/agent_run_params.py
swarms_client/types/agent_run_response.py
swarms_client/types/agent_spec_param.py
swarms_client/types/model_list_available_response.py
swarms_client/types/swarm_check_available_response.py
swarms_client/types/swarm_get_logs_response.py
swarms_client/types/swarm_run_params.py
swarms_client/types/swarm_run_response.py
swarms_client/types/swarm_spec_param.py
swarms_client/types/agent/__init__.py
swarms_client/types/agent/batch_run_params.py
swarms_client/types/agent/batch_run_response.py
swarms_client/types/swarms/__init__.py
swarms_client/types/swarms/batch_run_params.py
swarms_client/types/swarms/batch_run_response.py
swarms_client-0.2.0.dist-info/METADATA
swarms_client-0.2.0.dist-info/WHEEL
swarms_client-0.2.0.dist-info/licenses/LICENSE
swarms_client-0.2.0.dist-info/RECORD
